tbaapi/tba.py
tbaapi-0.1.dist-info/LICENSE
tbaapi-0.1.dist-info/METADATA
tbaapi-0.1.dist-info/WHEEL
tbaapi-0.1.dist-info/top_level.txt
tbaapi-0.1.dist-info/RECORD
