Metadata-Version: 2.1
Name: tbaapi
Version: 0.1
Summary: General api connection to The Blue Alliance
Author-email: Kellen Watt <kellen@wattsoft.dev>
Requires-Python: >=3.8
License-File: LICENSE
